dstar/__init__.py
dstar/darkstar.py
dstar-0.0.1.dist-info/METADATA
dstar-0.0.1.dist-info/WHEEL
dstar-0.0.1.dist-info/RECORD
